.gitlab-ci.yml
CHANGELOG.rst
LICENSE
MANIFEST.in
Makefile
README.rst
requirements.txt
setup.py
docs/Makefile
docs/changelog.rst
docs/conf.py
docs/enzymes.rst
docs/index.rst
docs/modules.rst
docs/readme.rst
docs/rpg.rst
docs/userguide.rst
rpg/RapidPeptidesGenerator.py
rpg/__init__.py
rpg/context.py
rpg/core.py
rpg/digest.py
rpg/enzyme.py
rpg/enzymes_definition.py
rpg/finder.py
rpg/rule.py
rpg/sequence.py
rpg.egg-info/PKG-INFO
rpg.egg-info/SOURCES.txt
rpg.egg-info/dependency_links.txt
rpg.egg-info/entry_points.txt
rpg.egg-info/requires.txt
rpg.egg-info/top_level.txt
tests/__init__.py
tests/context.py
tests/test_RapidPeptidesGenerator.py
tests/test_core.py
tests/test_digest.py
tests/test_enzyme.py
tests/test_functional.py
tests/test_rule.py
tests/test_sequence.py