Metadata-Version: 2.1
Name: rpg
Version: 2.0.2
Summary: In silico protein digestion
Home-page: https://gitlab.pasteur.fr/nmaillet/rpg
Author: Maillet Nicolas
Author-email: nicolas.maillet@pasteur.fr
Project-URL: Doc, https://rapid-peptide-generator.readthedocs.io/en/latest/
Keywords: protein,peptide,enzyme,protease,digestion
Classifier: Development Status :: 5 - Production/Stable
Classifier: Intended Audience :: Science/Research
Classifier: Topic :: Scientific/Engineering :: Bio-Informatics
Classifier: License :: OSI Approved :: GNU General Public License v3 or later (GPLv3+)
Classifier: Programming Language :: Python :: 3.6
Classifier: Programming Language :: Python :: 3.7
Classifier: Programming Language :: Python :: 3.8
Classifier: Programming Language :: Python :: 3.9
Classifier: Programming Language :: Python :: 3.10
Classifier: Programming Language :: Python :: 3.11
Requires-Python: >=3.6
License-File: LICENSE
Provides-Extra: test
Requires-Dist: pytest; extra == "test"
Requires-Dist: pytest-cov; extra == "test"
